django_modelables-0.1.dist-info/DESCRIPTION.rst
django_modelables-0.1.dist-info/METADATA
django_modelables-0.1.dist-info/RECORD
django_modelables-0.1.dist-info/WHEEL
django_modelables-0.1.dist-info/metadata.json
django_modelables-0.1.dist-info/top_level.txt
modelables/__init__.py
modelables/apps.py
modelables/behaviors.py
modelables/querysets.py
modelables/tests.py
modelables/migrations/__init__.py
