Metadata-Version: 2.0
Name: django-modelables
Version: 0.1
Summary: Django utilities that add model behaviors.
Home-page: https://github.com/fenikso/django-modelables/
Author: fenikso
Author-email: rogerpons@example.com
License: GNU General Public License v2 (GPLv2)
Platform: UNKNOWN
Classifier: Environment :: Web Environment
Classifier: Framework :: Django
Classifier: Framework :: Django :: 1.9
Classifier: Intended Audience :: Developers
Classifier: License :: OSI Approved :: GNU General Public License v2 (GPLv2)
Classifier: Operating System :: OS Independent
Classifier: Programming Language :: Python
Classifier: Programming Language :: Python :: 2.7
Classifier: Topic :: Internet :: WWW/HTTP
Classifier: Topic :: Internet :: WWW/HTTP :: Dynamic Content
